agent/AGENT_INSTRUCTIONS.md
agent/__init__.py
agent/server.py
agent/scripts/attach-fabric-git.ps1
agent/scripts/attach-log-analytics.ps1
agent/scripts/attach-nsp.ps1
agent/scripts/check-resource.ps1
agent/scripts/create-devops-branch.ps1
agent/scripts/create-devops-pipeline.ps1
agent/scripts/create-devops-project.ps1
agent/scripts/create-devops-repo.ps1
agent/scripts/create-fabric-workspace.ps1
agent/scripts/create-resourcegroup.ps1
agent/scripts/deploy-bicep.ps1
agent/scripts/deploy-pipeline-yaml.ps1
agent/scripts/list-azure-permissions.ps1
agent/scripts/list-devops-projects.ps1
agent/scripts/list-devops-repos.ps1
agent/scripts/list-fabric-permissions.ps1
agent/scripts/list-resources.ps1
agent/scripts/post-deploy-function-app.ps1
agent/templates/CodeQL_1ES_Pipeline.yml
agent/templates/CodeQL_Pipeline.yml
agent/templates/ai-foundry.bicep
agent/templates/ai-search.bicep
agent/templates/azure-data-factory.bicep
agent/templates/azure-key-vaults.bicep
agent/templates/azure-openai.bicep
agent/templates/azure-synapse-analytics.bicep
agent/templates/container-registry.bicep
agent/templates/cosmos-db.bicep
agent/templates/fabric-capacity.bicep
agent/templates/function-app.bicep
agent/templates/log-analytics.bicep
agent/templates/network-security-perimeter.bicep
agent/templates/public-ip.bicep
agent/templates/storage-account.bicep
agent/templates/user-assigned-managed-identity.bicep
azuresfimcpagent_test-2.0.5.dist-info/LICENSE
azuresfimcpagent_test-2.0.5.dist-info/METADATA
azuresfimcpagent_test-2.0.5.dist-info/WHEEL
azuresfimcpagent_test-2.0.5.dist-info/entry_points.txt
azuresfimcpagent_test-2.0.5.dist-info/top_level.txt
azuresfimcpagent_test-2.0.5.dist-info/RECORD
