Metadata-Version: 2.1
Name: azuresfimcpagent-test
Version: 2.0.5
Summary: Azure MCP Agent for secure, compliant resource deployment
Author: Siddhant Jha
Project-URL: Homepage, https://github.com/yourusername/azure-sfi-agent
Project-URL: Repository, https://github.com/yourusername/azure-sfi-agent
Project-URL: Issues, https://github.com/yourusername/azure-sfi-agent/issues
Keywords: mcp,azure,deployment,bicep,agent,sfi
Classifier: Development Status :: 4 - Beta
Classifier: Intended Audience :: Developers
Classifier: License :: OSI Approved :: MIT License
Classifier: Programming Language :: Python :: 3
Classifier: Programming Language :: Python :: 3.10
Classifier: Programming Language :: Python :: 3.11
Classifier: Programming Language :: Python :: 3.12
Classifier: Operating System :: OS Independent
Requires-Python: >=3.10
License-File: LICENSE
Requires-Dist: mcp>=0.1.0
